prghorselib/__init__.py
prghorselib/database.py
prghorselib/hash.py
prghorselib/os.py
prghorselib/random.py
prghorselib/time.py
prghorselib/web.py
prghorselib-0.0.3.dist-info/LICENSE
prghorselib-0.0.3.dist-info/METADATA
prghorselib-0.0.3.dist-info/WHEEL
prghorselib-0.0.3.dist-info/top_level.txt
prghorselib-0.0.3.dist-info/RECORD
