Metadata-Version: 2.1
Name: prghorselib
Version: 0.0.3
Summary: A library specifically for the prghorse team
Home-page: https://github.com/alxprgs/prghorselib
Author: Alx
Author-email: proshka20081010@gmail.com
Keywords: prghorse
Classifier: Programming Language :: Python :: 3.11
Classifier: License :: OSI Approved :: MIT License
Classifier: Operating System :: OS Independent
Requires-Python: >=3.10
License-File: LICENSE
Requires-Dist: motor>=3.6.0
Requires-Dist: fastapi>=0.115.5
Requires-Dist: psutil>=6.1.1
